wechat_django/__init__.py
wechat_django/apps.py
wechat_django/client.py
wechat_django/constants.py
wechat_django/exceptions.py
wechat_django/handler.py
wechat_django/requests.py
wechat_django/settings.py
wechat_django/signals.py
wechat_django/admin/__init__.py
wechat_django/admin/base.py
wechat_django/admin/utils.py
wechat_django/admin/wechatapp.py
wechat_django/admin/views/__init__.py
wechat_django/admin/views/article.py
wechat_django/admin/views/material.py
wechat_django/admin/views/menu.py
wechat_django/admin/views/messagehandler.py
wechat_django/admin/views/messagelog.py
wechat_django/admin/views/template.py
wechat_django/admin/views/user.py
wechat_django/admin/views/usertag.py
wechat_django/locale/zh/LC_MESSAGES/django.mo
wechat_django/locale/zh/LC_MESSAGES/django.po
wechat_django/migrations/0001_init.py
wechat_django/migrations/__init__.py
wechat_django/models/__init__.py
wechat_django/models/ability.py
wechat_django/models/app.py
wechat_django/models/article.py
wechat_django/models/base.py
wechat_django/models/constants.py
wechat_django/models/material.py
wechat_django/models/menu.py
wechat_django/models/messagehandler.py
wechat_django/models/messagelog.py
wechat_django/models/permission.py
wechat_django/models/reply.py
wechat_django/models/rule.py
wechat_django/models/session.py
wechat_django/models/template.py
wechat_django/models/user.py
wechat_django/models/usertag.py
wechat_django/oauth/__init__.py
wechat_django/oauth/authentication.py
wechat_django/oauth/client.py
wechat_django/oauth/mixins.py
wechat_django/oauth/permissions.py
wechat_django/oauth/request.py
wechat_django/oauth/views.py
wechat_django/pay/__init__.py
wechat_django/pay/apps.py
wechat_django/pay/client.py
wechat_django/pay/exceptions.py
wechat_django/pay/notify.py
wechat_django/pay/settings.py
wechat_django/pay/signals.py
wechat_django/pay/admin/__init__.py
wechat_django/pay/admin/base.py
wechat_django/pay/admin/order.py
wechat_django/pay/admin/payapp.py
wechat_django-0.4.0.dist-info/LICENCE
wechat_django-0.4.0.dist-info/METADATA
wechat_django-0.4.0.dist-info/WHEEL
wechat_django-0.4.0.dist-info/top_level.txt
wechat_django-0.4.0.dist-info/RECORD
