Metadata-Version: 2.1
Name: wechat-django
Version: 0.4.0
Summary: Django WeChat Extension
Home-page: https://github.com/Xavier-Lam/wechat-django
Author: Xavier-Lam
Author-email: xavierlam7@hotmail.com
Keywords: WeChat,weixin,wx,WeChatPay,micromessenger,django,微信,微信支付
Classifier: Development Status :: 2 - Pre-Alpha
Classifier: Environment :: Web Environment
Classifier: Framework :: Django :: 3.2
Classifier: Framework :: Django :: 4.0
Classifier: Framework :: Django :: 4.1
Classifier: Framework :: Django :: 4.2
Classifier: Framework :: Django :: 5.0
Classifier: Framework :: Django :: 5.1
Classifier: Intended Audience :: Developers
Classifier: License :: OSI Approved :: MIT License
Classifier: Natural Language :: Chinese (Simplified)
Classifier: Natural Language :: Chinese (Traditional)
Classifier: Natural Language :: English
Classifier: Operating System :: MacOS
Classifier: Operating System :: Microsoft :: Windows
Classifier: Operating System :: POSIX
Classifier: Operating System :: POSIX :: Linux
Classifier: Programming Language :: Python
Classifier: Programming Language :: Python :: 3.7
Classifier: Programming Language :: Python :: 3.8
Classifier: Programming Language :: Python :: 3.9
Classifier: Programming Language :: Python :: 3.10
Classifier: Programming Language :: Python :: 3.11
Classifier: Programming Language :: Python :: Implementation :: CPython
Classifier: Topic :: Internet :: WWW/HTTP
Classifier: Topic :: Internet :: WWW/HTTP :: Dynamic Content
Classifier: Topic :: Internet :: WWW/HTTP :: Site Management
Classifier: Topic :: Software Development :: Libraries
Classifier: Topic :: Software Development :: Libraries :: Application Frameworks
Classifier: Topic :: Software Development :: Libraries :: Python Modules
Classifier: Topic :: Utilities
License-File: LICENCE
Requires-Dist: Django>=3.2
Requires-Dist: django-object-tool>=0.0.9
Requires-Dist: pytz
Requires-Dist: requests>=2.4.3
Requires-Dist: wechatpy>=1.8.3
Provides-Extra: cryptography
Requires-Dist: cryptography; extra == "cryptography"
Provides-Extra: pycrypto
Requires-Dist: pycryptodome; extra == "pycrypto"
